wilos
