Metadata-Version: 1.1
Name: wilos-cli
Version: 0.1.0.1
Summary: What's it like outside? - Weather for hackers
Home-page: https://github.com/aslan11/wilos-cli
Author: Kevin Martin
Author-email: kvn.p.mrtn@gmail.com
License: MIT
Keywords: live weather tool cli google darksky forecast
Platform: UNKNOWN
Classifier: Development Status :: 3 - Alpha
Classifier: Intended Audience :: Developers
Classifier: Topic :: Software Development :: Build Tools
Classifier: License :: OSI Approved :: MIT License
Classifier: Programming Language :: Python :: 2
Classifier: Programming Language :: Python :: 2.6
Classifier: Programming Language :: Python :: 2.7
